{
  "metrics": {
    "compile-time-unix-x86_64-8.stddev": 98,
    "compile-time-unix-x86_64-8.min": 111544,
    "compile-time-unix-x86_64-16.median": 72038,
    "compile-time-unix-x86_64-16.mean": 72021,
    "compile-time-unix-x86_64-8.mean": 111675,
    "compile-time-unix-x86_64-16.stddev": 444,
    "compile-time-unix-x86_64-16.min": 71419,
    "compile-time-unix-x86_64-8.median": 111641,
    "compile-time-unix-x86_64-8.system": 22277,
    "compile-time-unix-x86_64-16.user": 1055158,
    "compile-time-unix-x86_64-8.user": 839053,
    "native-unix-x86_64.size": 100417392,
    "compile-time-unix-x86_64-16.system": 27768,
    "compile-time-unix-x86_64-16.max": 72615,
    "compile-time-unix-x86_64-8.max": 111822
  },
  "commit": "b01de70bdd927bcc9cdc5d0b8c677f480e54f4b1",
  "timestamp": 1751991004806,
  "commit_timestamp": 1751585795000,
  "rust": {
    "stable": "rustc 1.88.0 (6b00bc388 2025-06-23)",
    "nightly": "rustc 1.90.0-nightly (3014e79f9 2025-07-15)"
  },
  "host": {
    "hostname": "bevy-bench-01",
    "os_version": "6.11.0-29-generic"
  }
}
